_init_.py
conf.py
ingest_data.py
main.py
ml_log.py
nonstandardcode.py
score.py
train.py
durgamba_housing-0.0.1.dist-info/METADATA
durgamba_housing-0.0.1.dist-info/WHEEL
durgamba_housing-0.0.1.dist-info/top_level.txt
durgamba_housing-0.0.1.dist-info/RECORD
