Metadata-Version: 2.1
Name: durgamba-housing
Version: 0.0.1
Requires-Dist: requests
Requires-Dist: importlib-metadata ; python_version == "3.8"
